OlivOS/nonebot/__init__.py
OlivOS/nonebot/plugin.py
OlivOS/nonebot/middlewares/__init__.py
OlivOS/nonebot/middlewares/onebot.py
OlivOS/nonebot/middlewares/telegram.py
OlivOS.nb2-0.2.3.dist-info/LICENSE
OlivOS.nb2-0.2.3.dist-info/METADATA
OlivOS.nb2-0.2.3.dist-info/WHEEL
OlivOS.nb2-0.2.3.dist-info/top_level.txt
OlivOS.nb2-0.2.3.dist-info/RECORD
