Metadata-Version: 2.1
Name: OlivOS.nb2
Version: 0.2.3
Summary: Load OlivOS plugin in NoneBot2
Author-email: jigsaw <j1g5awi@proton.me>
License: AGPL-3.0-only
Requires-Python: <4.0,>=3.9
License-File: LICENSE
Requires-Dist: olivos<1.0.0,>=0.10.2
Requires-Dist: nonebot2<3.0.0,>=2.0.0
Provides-Extra: onebot
Requires-Dist: nonebot-adapter-onebot<3.0.0.0,>=2.2.2; extra == "onebot"
Provides-Extra: telegram
Requires-Dist: nonebot-adapter-telegram<1.0.0.0,>=0.1.0b13; extra == "telegram"
